{
    "name": "RGBA",
    "shortName": "",
    "manufacturer": "Generic",
    "type": "static",
    "numChannels": 4,
    "channels": [
        {
            "type": "color",
            "subtype": "red",
            "name": "Red",
            "max": 255,
            "min": 0,
            "displayMax": 100,
            "displayMin": 0,
            "value": 0,
            "displayValue": 0,
            "defaultValue": 0,
            "dmxAddressOffset": 0,
            "locked": false
        },
        {
            "type": "color",
            "subtype": "green",
            "name": "Green",
            "max": 255,
            "min": 0,
            "displayMax": 100,
            "displayMin": 0,
            "value": 0,
            "displayValue": 0,
            "defaultValue": 0,
            "dmxAddressOffset": 1,
            "locked": false
        },
        {
            "type": "color",
            "subtype": "blue",
            "name": "Blue",
            "max": 255,
            "min": 0,
            "displayMax": 100,
            "displayMin": 0,
            "value": 0,
            "displayValue": 0,
            "defaultValue": 0,
            "dmxAddressOffset": 2,
            "locked": false
        },
        {
            "type": "color",
            "subtype": "amber",
            "name": "Amber",
            "max": 255,
            "min": 0,
            "displayMax": 100,
            "displayMin": 0,
            "value": 0,
            "displayValue": 0,
            "defaultValue": 0,
            "dmxAddressOffset": 3,
            "locked": false
        }
    ],
    "chips": []
}